<?xml version="1.0" encoding="utf-8"?>
<!DOCTYPE hibernate-mapping PUBLIC "-//Hibernate/Hibernate Mapping DTD 3.0//EN"
                                   "http://www.hibernate.org/dtd/hibernate-mapping-3.0.dtd">
<!-- 
    Mapping file autogenerated by MyEclipse Persistence Tools
-->
<hibernate-mapping>
 <class catalog="test" name="org.jncc.base.software.ESoftware" table="e_software">
  <composite-id class="org.jncc.base.software.ESoftwareId"
   mapped="false" name="id" unsaved-value="undefined">
   <key-property name="name" type="java.lang.String">
    <column length="128" name="name"/>
   </key-property>
   <key-property name="zone" type="java.lang.String">
    <column length="16" name="zone"/>
   </key-property>
  </composite-id>
  <property generated="never" lazy="false" name="createdate" type="java.lang.String">
   <column length="10" name="createdate"/>
  </property>
  <property generated="never" lazy="false" name="os" type="java.lang.String">
   <column length="64" name="os"/>
  </property>
  <property generated="never" lazy="false" name="operator" type="java.lang.String">
   <column length="32" name="operator"/>
  </property>
  <property generated="never" lazy="false" name="comment" type="java.lang.String">
   <column length="128" name="comment"/>
  </property>
 </class>
</hibernate-mapping>
